sqtpy/__init__.py
sqtpy/sqtpy.py
sqtpy/sample_data/Acknowledgements.txt
sqtpy/sample_data/demo.ipynb
sqtpy/sample_data/female.wav
sqtpy/sample_data/female_sqt.wav
sqtpy/sample_data/infant.wav
sqtpy/sample_data/infant_sqt.wav
sqtpy/sample_data/male.wav
sqtpy/sample_data/male_sqt.wav
sqtpy-0.0.4.dist-info/LICENSE
sqtpy-0.0.4.dist-info/METADATA
sqtpy-0.0.4.dist-info/WHEEL
sqtpy-0.0.4.dist-info/top_level.txt
sqtpy-0.0.4.dist-info/RECORD
