Metadata-Version: 2.1
Name: sqtpy
Version: 0.0.4
Summary: Speech Extractor and Reconstructor
Home-page: https://github.com/hasanainaz/sqt
Author: Ahmad Hasanain
Author-email: hasanainaz@gmail.com
Keywords: ASR,Pitch Track,Speech Reconstruction,Speech Processing,Cepstrogram,Singal Processing
Classifier: License :: OSI Approved :: GNU Affero General Public License v3
Classifier: Development Status :: 5 - Production/Stable
Classifier: Operating System :: OS Independent
Classifier: Programming Language :: Python :: 3
Classifier: Framework :: Jupyter
Classifier: Framework :: IPython
Classifier: Topic :: Multimedia :: Sound/Audio :: Speech
Classifier: Topic :: Multimedia :: Sound/Audio :: Analysis
Classifier: Topic :: Multimedia :: Sound/Audio :: Sound Synthesis
Classifier: Topic :: Scientific/Engineering :: Artificial Intelligence
Classifier: Topic :: Scientific/Engineering :: Human Machine Interfaces
Classifier: Topic :: Scientific/Engineering :: Image Processing
Classifier: Intended Audience :: Science/Research
Classifier: Intended Audience :: Telecommunications Industry
Classifier: Intended Audience :: Developers
License-File: LICENSE
